MANIFEST.in
README.rst
setup.py
myapp810/__init__.py
myapp810/utils.py
myapp810.egg-info/PKG-INFO
myapp810.egg-info/SOURCES.txt
myapp810.egg-info/dependency_links.txt
myapp810.egg-info/requires.txt
myapp810.egg-info/top_level.txt