Metadata-Version: 1.0
Name: myapp810
Version: 0.0.4
Summary: 114 514
Home-page: https://github.com/me/hhh
Author: me
Author-email: me@etwings.com
License: MIT
Platform: UNKNOWN
